{
  "base": "20260128_goran_granic_neprolazna_slava_yt_z4QKgZLLZ3g",
  "channel": "nanovoroeni",
  "target": {
    "I": -16,
    "TP": -2,
    "LRA": 11
  },
  "method": "loudnorm single-pass dynamic (Dynamic)",
  "audio_source": {
    "file": "20260128_goran_granic_neprolazna_slava_yt_z4QKgZLLZ3g.mp4",
    "type": "mp4"
  },
  "input": {
    "integrated_lufs": -16.3,
    "true_peak_dbtp": -0.9,
    "lra": 8.9
  },
  "output": {
    "integrated_lufs": -15.3,
    "true_peak_dbtp": -2
  },
  "formats": {
    "mp3": {
      "output": "20260128_goran_granic_neprolazna_slava_yt_z4QKgZLLZ3g.loudnorm.mp3",
      "bitrate": "128k",
      "normalized_at": "2026-05-29T05:43:51.142Z"
    }
  }
}
