{
  "base": "20241206_podcast_53_andrea_oros_catholic_cro_woman_yt_cdXl1Cpc7VE",
  "channel": "mladi_za_domovinu",
  "target": {
    "I": -16,
    "TP": -2,
    "LRA": 11
  },
  "method": "loudnorm single-pass dynamic (Dynamic)",
  "audio_source": {
    "file": "20241206_podcast_53_andrea_oros_catholic_cro_woman_yt_cdXl1Cpc7VE.mkv",
    "type": "mkv"
  },
  "input": {
    "integrated_lufs": -28.1,
    "true_peak_dbtp": -3.8,
    "lra": 12.6
  },
  "output": {
    "integrated_lufs": -16.7,
    "true_peak_dbtp": -2
  },
  "formats": {
    "mp3": {
      "output": "20241206_podcast_53_andrea_oros_catholic_cro_woman_yt_cdXl1Cpc7VE.loudnorm.mp3",
      "bitrate": "128k",
      "normalized_at": "2026-05-29T03:07:51.893Z"
    }
  }
}
