{
  "base": "20240301_ddv_propovijed_bog_je_uvijek_na_strani_ostavljenih_yt_773ExN9tts8",
  "channel": "budi_frajer",
  "target": {
    "I": -16,
    "TP": -2,
    "LRA": 11
  },
  "method": "loudnorm single-pass dynamic (Dynamic)",
  "audio_source": {
    "file": "20240301_ddv_propovijed_bog_je_uvijek_na_strani_ostavljenih_yt_773ExN9tts8.mkv",
    "type": "mkv"
  },
  "input": {
    "integrated_lufs": -31,
    "true_peak_dbtp": -13.1,
    "lra": 7.2
  },
  "output": {
    "integrated_lufs": -15.9,
    "true_peak_dbtp": -2
  },
  "formats": {
    "mp3": {
      "output": "20240301_ddv_propovijed_bog_je_uvijek_na_strani_ostavljenih_yt_773ExN9tts8.loudnorm.mp3",
      "bitrate": "128k",
      "normalized_at": "2026-05-28T21:44:45.654Z"
    }
  }
}
