{"id": "H10klJy_5L8", "title": "ZABRANJENO KUKANJE - knjiga po Papinoj preporuci! // Kako se osloboditi kukanja?", "formats": [{"format_id": "sb2", "format_note": "storyboard", "ext": "mhtml", "protocol": "mhtml", "acodec": "none", "vcodec": "none", "url": "https://i.ytimg.com/sb/H10klJy_5L8/storyboard3_L0/default.jpg?sqp=-oaymwENSDfyq4qpAwVwAcABBqLzl_8DBgjw8YuXBg==&sigh=rs$AOn4CLD4lBGBtcGI433FZGu1uSZrR6DLlw", "width": 48, "height": 27, "fps": 0.09910802775024777, "rows": 10, "columns": 10, "fragments": [{"url": "https://i.ytimg.com/sb/H10klJy_5L8/storyboard3_L0/default.jpg?sqp=-oaymwENSDfyq4qpAwVwAcABBqLzl_8DBgjw8YuXBg==&sigh=rs$AOn4CLD4lBGBtcGI433FZGu1uSZrR6DLlw", "duration": 1009.0}], "audio_ext": "none", "video_ext": "none", "vbr": 0, "abr": 0, "resolution": "48x27", "aspect_ratio": 1.78, "http_headers": {"User-Agent": "Mozilla/5.0 (Macintosh; Intel Mac OS X 10_15_7) AppleWebKit/537.36 (KHTML, like Gecko) Chrome/144.0.0.0 Safari/537.36", "Accept": "text/html,application/xhtml+xml,application/xml;q=0.9,*/*;q=0.8", "Accept-Language": "en-us,en;q=0.5", "Sec-Fetch-Mode": "navigate"}, "format": "sb2 - 48x27 (storyboard)"}, {"format_id": "sb1", "format_note": "storyboard", "ext": "mhtml", "protocol": "mhtml", "acodec": "none", "vcodec": "none", "url": "https://i.ytimg.com/sb/H10klJy_5L8/storyboard3_L1/M$M.jpg?sqp=-oaymwENSDfyq4qpAwVwAcABBqLzl_8DBgjw8YuXBg==&sigh=rs$AOn4CLBZ-AahYUxY2clv7Rs5Cx9V_PIt1A", "width": 80, "height": 45, "fps": 0.10109018830525272, "rows": 10, "columns": 10, "fragments": [{"url": "https://i.ytimg.com/sb/H10klJy_5L8/storyboard3_L1/M0.jpg?sqp=-oaymwENSDfyq4qpAwVwAcABBqLzl_8DBgjw8YuXBg==&sigh=rs$AOn4CLBZ-AahYUxY2clv7Rs5Cx9V_PIt1A", "duration": 989.2156862745098}, {"url": "https://i.ytimg.com/sb/H10klJy_5L8/storyboard3_L1/M1.jpg?sqp=-oaymwENSDfyq4qpAwVwAcABBqLzl_8DBgjw8YuXBg==&sigh=rs$AOn4CLBZ-AahYUxY2clv7Rs5Cx9V_PIt1A", "duration": 19.784313725490165}], "audio_ext": "none", "video_ext": "none", "vbr": 0, "abr": 0, "resolution": "80x45", "aspect_ratio": 1.78, "http_headers": {"User-Agent": "Mozilla/5.0 (Macintosh; Intel Mac OS X 10_15_7) AppleWebKit/537.36 (KHTML, like Gecko) Chrome/144.0.0.0 Safari/537.36", "Accept": "text/html,application/xhtml+xml,application/xml;q=0.9,*/*;q=0.8", "Accept-Language": "en-us,en;q=0.5", "Sec-Fetch-Mode": "navigate"}, "format": "sb1 - 80x45 (storyboard)"}, {"format_id": "sb0", "format_note": "storyboard", "ext": "mhtml", "protocol": "mhtml", "acodec": "none", "vcodec": "none", "url": "https://i.ytimg.com/sb/H10klJy_5L8/storyboard3_L2/M$M.jpg?sqp=-oaymwENSDfyq4qpAwVwAcABBqLzl_8DBgjw8YuXBg==&sigh=rs$AOn4CLAJ3_tUcm-gG4pwFS_p6GE8PL4eAA", "width": 160, "height": 90, "fps": 0.10109018830525272, "rows": 5, "columns": 5, "fragments": [{"url": "https://i.ytimg.com/sb/H10klJy_5L8/storyboard3_L2/M0.jpg?sqp=-oaymwENSDfyq4qpAwVwAcABBqLzl_8DBgjw8YuXBg==&sigh=rs$AOn4CLAJ3_tUcm-gG4pwFS_p6GE8PL4eAA", "duration": 247.30392156862746}, {"url": "https://i.ytimg.com/sb/H10klJy_5L8/storyboard3_L2/M1.jpg?sqp=-oaymwENSDfyq4qpAwVwAcABBqLzl_8DBgjw8YuXBg==&sigh=rs$AOn4CLAJ3_tUcm-gG4pwFS_p6GE8PL4eAA", "duration": 247.30392156862746}, {"url": "https://i.ytimg.com/sb/H10klJy_5L8/storyboard3_L2/M2.jpg?sqp=-oaymwENSDfyq4qpAwVwAcABBqLzl_8DBgjw8YuXBg==&sigh=rs$AOn4CLAJ3_tUcm-gG4pwFS_p6GE8PL4eAA", "duration": 247.30392156862746}, {"url": "https://i.ytimg.com/sb/H10klJy_5L8/storyboard3_L2/M3.jpg?sqp=-oaymwENSDfyq4qpAwVwAcABBqLzl_8DBgjw8YuXBg==&sigh=rs$AOn4CLAJ3_tUcm-gG4pwFS_p6GE8PL4eAA", "duration": 247.30392156862746}, {"url": "https://i.ytimg.com/sb/H10klJy_5L8/storyboard3_L2/M4.jpg?sqp=-oaymwENSDfyq4qpAwVwAcABBqLzl_8DBgjw8YuXBg==&sigh=rs$AOn4CLAJ3_tUcm-gG4pwFS_p6GE8PL4eAA", "duration": 19.784313725490165}], "audio_ext": "none", "video_ext": "none", "vbr": 0, "abr": 0, "resolution": "160x90", "aspect_ratio": 1.78, "http_headers": {"User-Agent": "Mozilla/5.0 (Macintosh; Intel Mac OS X 10_15_7) AppleWebKit/537.36 (KHTML, like Gecko) Chrome/144.0.0.0 Safari/537.36", "Accept": "text/html,application/xhtml+xml,application/xml;q=0.9,*/*;q=0.8", "Accept-Language": "en-us,en;q=0.5", "Sec-Fetch-Mode": "navigate"}, "format": "sb0 - 160x90 (storyboard)"}, {"asr": 44100, "filesize": 16329559, "format_id": "140", "format_note": "medium", "source_preference": -1, "audio_channels": 2, "quality": 3.0, "has_drm": false, "tbr": 129.477, "filesize_approx": 16329525, "language_preference": -1, "ext": "m4a", "vcodec": "none", "acodec": "mp4a.40.2", "container": "m4a_dash", "url": "https://rr2---sn-v2uph5-15bl.googlevideo.com/videoplayback?expire=1771486998&ei=tmqWad6JB8zRp-oPn4qYoAE&ip=89.201.137.96&id=o-APkTk5Uee1RPQeTL8w9Pzpa1Rdl0B7eAWb25hqodAzuj&itag=140&source=youtube&requiressl=yes&xpc=EgVo2aDSNQ%3D%3D&cps=296&met=1771465398%2C&mh=iZ&mm=31%2C29&mn=sn-v2uph5-15bl%2Csn-4g5lznlz&ms=au%2Crdu&mv=m&mvi=2&pl=18&rms=au%2Cau&initcwndbps=1381250&siu=1&bui=AVNa5-yf63HS3uadg3T4kTGIF28DcrCQYbQ82e7wzj6PPEMtgkN4ABIQc9gcgx7y05IZdnTKxw&vprv=1&svpuc=1&mime=audio%2Fmp4&ns=-oQLUN7Q2868RpGNEmNHDDoS&rqh=1&gir=yes&clen=16329559&dur=1008.953&lmt=1659290272142056&mt=1771465040&fvip=4&keepalive=yes&lmw=1&fexp=51557447%2C51565115%2C51565681%2C51580970%2C51759074&c=TVHTML5&sefc=1&txp=5318224&n=7hP55SJY84Aidg&sparams=expire%2Cei%2Cip%2Cid%2Citag%2Csource%2Crequiressl%2Cxpc%2Csiu%2Cbui%2Cvprv%2Csvpuc%2Cmime%2Cns%2Crqh%2Cgir%2Cclen%2Cdur%2Clmt&sig=AJEij0EwRQIhALruM-WhpN2-Ci2khcYE80HGoGMksvwXauMN46ZsmRHqAiAiwA3awrzkISM85bW6AKYNFpk79bI5a50v41xjDHWwCw%3D%3D&lsparams=cps%2Cmet%2Cmh%2Cmm%2Cmn%2Cms%2Cmv%2Cmvi%2Cpl%2Crms%2Cinitcwndbps&lsig=APaTxxMwRQIgJJ1ExT2Sgn6XFqcV-JoWL57A7L7zcAFHEmBTJ8rhOskCIQCfZzXBiOqeN4lzfxq6PdpepP776AsG6AsZXAkL-k94tQ%3D%3D", "available_at": 1771465398, "downloader_options": {"http_chunk_size": 10485760}, "protocol": "https", "audio_ext": "m4a", "video_ext": "none", "vbr": 0, "abr": 129.477, "resolution": "audio only", "http_headers": {"User-Agent": "Mozilla/5.0 (Macintosh; Intel Mac OS X 10_15_7) AppleWebKit/537.36 (KHTML, like Gecko) Chrome/144.0.0.0 Safari/537.36", "Accept": "text/html,application/xhtml+xml,application/xml;q=0.9,*/*;q=0.8", "Accept-Language": "en-us,en;q=0.5", "Sec-Fetch-Mode": "navigate"}, "format": "140 - audio only (medium)"}, {"asr": 48000, "filesize": 12838502, "format_id": "251", "format_note": "medium", "source_preference": -1, "audio_channels": 2, "quality": 3.0, "has_drm": false, "tbr": 101.799, "filesize_approx": 12838393, "language_preference": -1, "ext": "webm", "vcodec": "none", "acodec": "opus", "container": "webm_dash", "url": "https://rr2---sn-v2uph5-15bl.googlevideo.com/videoplayback?expire=1771486998&ei=tmqWad6JB8zRp-oPn4qYoAE&ip=89.201.137.96&id=o-APkTk5Uee1RPQeTL8w9Pzpa1Rdl0B7eAWb25hqodAzuj&itag=251&source=youtube&requiressl=yes&xpc=EgVo2aDSNQ%3D%3D&cps=296&met=1771465398%2C&mh=iZ&mm=31%2C29&mn=sn-v2uph5-15bl%2Csn-4g5lznlz&ms=au%2Crdu&mv=m&mvi=2&pl=18&rms=au%2Cau&initcwndbps=1381250&siu=1&bui=AVNa5-yf63HS3uadg3T4kTGIF28DcrCQYbQ82e7wzj6PPEMtgkN4ABIQc9gcgx7y05IZdnTKxw&vprv=1&svpuc=1&mime=audio%2Fwebm&ns=-oQLUN7Q2868RpGNEmNHDDoS&rqh=1&gir=yes&clen=12838502&dur=1008.921&lmt=1659290336489906&mt=1771465040&fvip=4&keepalive=yes&lmw=1&fexp=51557447%2C51565115%2C51565681%2C51580970%2C51759074&c=TVHTML5&sefc=1&txp=5318224&n=7hP55SJY84Aidg&sparams=expire%2Cei%2Cip%2Cid%2Citag%2Csource%2Crequiressl%2Cxpc%2Csiu%2Cbui%2Cvprv%2Csvpuc%2Cmime%2Cns%2Crqh%2Cgir%2Cclen%2Cdur%2Clmt&sig=AJEij0EwRQIgAdkBNLt9z3DA9tf8TkyQeA2iT1pccdRjKlarX2xEjBYCIQCR43EOedFOXd0uEQjtMKgwtr4Me2K6ZGXNF9DYFpINLw%3D%3D&lsparams=cps%2Cmet%2Cmh%2Cmm%2Cmn%2Cms%2Cmv%2Cmvi%2Cpl%2Crms%2Cinitcwndbps&lsig=APaTxxMwRQIgJJ1ExT2Sgn6XFqcV-JoWL57A7L7zcAFHEmBTJ8rhOskCIQCfZzXBiOqeN4lzfxq6PdpepP776AsG6AsZXAkL-k94tQ%3D%3D", "available_at": 1771465398, "downloader_options": {"http_chunk_size": 10485760}, "protocol": "https", "audio_ext": "webm", "video_ext": "none", "vbr": 0, "abr": 101.799, "resolution": "audio only", "http_headers": {"User-Agent": "Mozilla/5.0 (Macintosh; Intel Mac OS X 10_15_7) AppleWebKit/537.36 (KHTML, like Gecko) Chrome/144.0.0.0 Safari/537.36", "Accept": "text/html,application/xhtml+xml,application/xml;q=0.9,*/*;q=0.8", "Accept-Language": "en-us,en;q=0.5", "Sec-Fetch-Mode": "navigate"}, "format": "251 - audio only (medium)"}, {"format_id": "91", "url": "https://manifest.googlevideo.com/api/manifest/hls_playlist/expire/1771486998/ei/tmqWaabTHPeEp-oPhMnRkAg/ip/89.201.137.96/id/1f5d24949cbfe4bf/itag/91/source/youtube/requiressl/yes/ratebypass/yes/pfa/1/sgoap/clen%3D6153689%3Bdur%3D1008.999%3Bgir%3Dyes%3Bitag%3D139%3Blmt%3D1659290272118788/sgovp/clen%3D6891654%3Bdur%3D1008.874%3Bgir%3Dyes%3Bitag%3D160%3Blmt%3D1659291502268163/rqh/1/hls_chunk_host/rr2---sn-v2uph5-15bl.googlevideo.com/xpc/EgVo2aDSNQ%3D%3D/cps/301/met/1771465398,/mh/iZ/mm/31,29/mn/sn-v2uph5-15bl,sn-4g5lznlz/ms/au,rdu/mv/m/mvi/2/pl/18/rms/au,au/initcwndbps/1381250/siu/1/bui/AVNa5-y7i3PaLcsnsmCsFzb1k8LP2OcGpISlBzUou0f-z8n-QWRjhv-n_sXFNWRtV5zU15TUng/spc/6dlaFFE1c59rotXWGMW_Riy9bK3-Ac38KLMKJOjLWzbzQhAqJpnLXKjJaPqfw207vX8Kd8BWNg/vprv/1/ns/Uf-YSjX6FTBnFx5chVngiDoS/playlist_type/CLEAN/dover/11/txp/5319224/mt/1771465040/fvip/4/keepalive/yes/fexp/51552689,51565115,51565681,51580968/n/5QXbrVPaUL9xXA/sparams/expire,ei,ip,id,itag,source,requiressl,ratebypass,pfa,sgoap,sgovp,rqh,xpc,siu,bui,spc,vprv,ns,playlist_type/sig/AJEij0EwRQIgajLoTlz6TjrwoXHOYlJK_NoDkiIPeRcM7CL4WTWdvmoCIQDbYR3lvfTH4m9xxu4JVHRCJJVTWYSJp79Og1358ll1QQ%3D%3D/lsparams/hls_chunk_host,cps,met,mh,mm,mn,ms,mv,mvi,pl,rms,initcwndbps/lsig/APaTxxMwRQIhAOc-FEYx5HnCcqJ0yYmWesim9yoGSHbg8CzUCBYFwYsrAiA9Qm5ED5TlMfuWVhcgKGGDdSyA9HmYvYMRl5E31YN8dw%3D%3D/playlist/index.m3u8", "manifest_url": "https://manifest.googlevideo.com/api/manifest/hls_variant/expire/1771486998/ei/tmqWaabTHPeEp-oPhMnRkAg/ip/89.201.137.96/id/1f5d24949cbfe4bf/source/youtube/requiressl/yes/xpc/EgVo2aDSNQ%3D%3D/playback_host/rr2---sn-v2uph5-15bl.googlevideo.com/cps/301/met/1771465398%2C/mh/iZ/mm/31%2C29/mn/sn-v2uph5-15bl%2Csn-4g5lznlz/ms/au%2Crdu/mv/m/mvi/2/pl/18/rms/au%2Cau/tx/0/txs/51691027%2C51691028/hfr/1/maxh/4320/tts_caps/1/maudio/1/initcwndbps/1381250/siu/1/bui/AVNa5-y7i3PaLcsnsmCsFzb1k8LP2OcGpISlBzUou0f-z8n-QWRjhv-n_sXFNWRtV5zU15TUng/spc/6dlaFFE1c59rotXWGMW_Riy9bK3-Ac38KLMKJOjLWzbzQhAqJpnLXKjJaPqfw207vX8Kd8BWNg/vprv/1/go/1/ns/Uf-YSjX6FTBnFx5chVngiDoS/rqh/5/mt/1771465040/fvip/4/nvgoi/1/ncsapi/1/keepalive/yes/fexp/51552689%2C51565115%2C51565681%2C51580968/dover/11/n/5QXbrVPaUL9xXA/itag/0/playlist_type/CLEAN/sparams/expire%2Cei%2Cip%2Cid%2Csource%2Crequiressl%2Cxpc%2Ctx%2Ctxs%2Chfr%2Cmaxh%2Ctts_caps%2Cmaudio%2Csiu%2Cbui%2Cspc%2Cvprv%2Cgo%2Cns%2Crqh%2Citag%2Cplaylist_type/sig/AJEij0EwRQIhAM_IG0MpoB93ZlTshxjliV4kYhOLDkH94QA2k34Y99lEAiAPVQR4KyfXusxQg63wuKrDw2R78-ZFQip5qWr6Dh-xvw%3D%3D/lsparams/playback_host%2Ccps%2Cmet%2Cmh%2Cmm%2Cmn%2Cms%2Cmv%2Cmvi%2Cpl%2Crms%2Cinitcwndbps/lsig/APaTxxMwRgIhAI6UfH4FYgt3iMgPvDqx4wKtWc-Ds7e_LZQPLq9xTLBSAiEAwWRybtxu53IzGJDT0_uBJDQKKCP9IlaaBbvF98PICKM%3D/file/index.m3u8", "tbr": 140.976, "ext": "mp4", "fps": 30.0, "protocol": "m3u8_native", "quality": 0, "has_drm": false, "width": 256, "height": 144, "vcodec": "avc1.4D400C", "acodec": "mp4a.40.5", "dynamic_range": "SDR", "available_at": 1771465404, "source_preference": -2, "video_ext": "mp4", "audio_ext": "none", "resolution": "256x144", "aspect_ratio": 1.78, "http_headers": {"User-Agent": "Mozilla/5.0 (Macintosh; Intel Mac OS X 10_15_7) AppleWebKit/537.36 (KHTML, like Gecko) Chrome/144.0.0.0 Safari/537.36", "Accept": "text/html,application/xhtml+xml,application/xml;q=0.9,*/*;q=0.8", "Accept-Language": "en-us,en;q=0.5", "Sec-Fetch-Mode": "navigate"}, "format": "91 - 256x144"}, {"filesize": 6891654, "format_id": "160", "format_note": "144p", "source_preference": -1, "fps": 30, "height": 144, "quality": 0.0, "has_drm": false, "tbr": 54.648, "filesize_approx": 6891618, "width": 256, "language_preference": -1, "ext": "mp4", "vcodec": "avc1.4d400c", "acodec": "none", "dynamic_range": "SDR", "container": "mp4_dash", "url": "https://rr2---sn-v2uph5-15bl.googlevideo.com/videoplayback?expire=1771486998&ei=tmqWad6JB8zRp-oPn4qYoAE&ip=89.201.137.96&id=o-APkTk5Uee1RPQeTL8w9Pzpa1Rdl0B7eAWb25hqodAzuj&itag=160&aitags=134%2C136%2C160%2C243&source=youtube&requiressl=yes&xpc=EgVo2aDSNQ%3D%3D&cps=296&met=1771465398%2C&mh=iZ&mm=31%2C29&mn=sn-v2uph5-15bl%2Csn-4g5lznlz&ms=au%2Crdu&mv=m&mvi=2&pl=18&rms=au%2Cau&initcwndbps=1381250&siu=1&bui=AVNa5-yf63HS3uadg3T4kTGIF28DcrCQYbQ82e7wzj6PPEMtgkN4ABIQc9gcgx7y05IZdnTKxw&vprv=1&svpuc=1&mime=video%2Fmp4&ns=-oQLUN7Q2868RpGNEmNHDDoS&rqh=1&gir=yes&clen=6891654&dur=1008.874&lmt=1659291502268163&mt=1771465040&fvip=4&keepalive=yes&lmw=1&fexp=51557447%2C51565115%2C51565681%2C51580970%2C51759074&c=TVHTML5&sefc=1&txp=5319224&n=7hP55SJY84Aidg&sparams=expire%2Cei%2Cip%2Cid%2Caitags%2Csource%2Crequiressl%2Cxpc%2Csiu%2Cbui%2Cvprv%2Csvpuc%2Cmime%2Cns%2Crqh%2Cgir%2Cclen%2Cdur%2Clmt&sig=AJEij0EwRAIgLvPyvfQzaDzOVx5hV5YQCfK8cZbyxOSUbT41KahIFy0CIGrGvbkUU0zEMvkKi0Zl2ON5_dxlGQ-_Ecnuxo8pB4Vy&lsparams=cps%2Cmet%2Cmh%2Cmm%2Cmn%2Cms%2Cmv%2Cmvi%2Cpl%2Crms%2Cinitcwndbps&lsig=APaTxxMwRQIgJJ1ExT2Sgn6XFqcV-JoWL57A7L7zcAFHEmBTJ8rhOskCIQCfZzXBiOqeN4lzfxq6PdpepP776AsG6AsZXAkL-k94tQ%3D%3D", "available_at": 1771465398, "downloader_options": {"http_chunk_size": 10485760}, "protocol": "https", "video_ext": "mp4", "audio_ext": "none", "abr": 0, "vbr": 54.648, "resolution": "256x144", "aspect_ratio": 1.78, "http_headers": {"User-Agent": "Mozilla/5.0 (Macintosh; Intel Mac OS X 10_15_7) AppleWebKit/537.36 (KHTML, like Gecko) Chrome/144.0.0.0 Safari/537.36", "Accept": "text/html,application/xhtml+xml,application/xml;q=0.9,*/*;q=0.8", "Accept-Language": "en-us,en;q=0.5", "Sec-Fetch-Mode": "navigate"}, "format": "160 - 256x144 (144p)"}, {"format_id": "93", "url": "https://manifest.googlevideo.com/api/manifest/hls_playlist/expire/1771486998/ei/tmqWaabTHPeEp-oPhMnRkAg/ip/89.201.137.96/id/1f5d24949cbfe4bf/itag/93/source/youtube/requiressl/yes/ratebypass/yes/pfa/1/sgoap/clen%3D16329559%3Bdur%3D1008.953%3Bgir%3Dyes%3Bitag%3D140%3Blmt%3D1659290272142056/sgovp/clen%3D27944192%3Bdur%3D1008.874%3Bgir%3Dyes%3Bitag%3D134%3Blmt%3D1659291511089322/rqh/1/hls_chunk_host/rr2---sn-v2uph5-15bl.googlevideo.com/xpc/EgVo2aDSNQ%3D%3D/cps/301/met/1771465398,/mh/iZ/mm/31,29/mn/sn-v2uph5-15bl,sn-4g5lznlz/ms/au,rdu/mv/m/mvi/2/pl/18/rms/au,au/initcwndbps/1381250/siu/1/bui/AVNa5-y7i3PaLcsnsmCsFzb1k8LP2OcGpISlBzUou0f-z8n-QWRjhv-n_sXFNWRtV5zU15TUng/spc/6dlaFFE1c59rotXWGMW_Riy9bK3-Ac38KLMKJOjLWzbzQhAqJpnLXKjJaPqfw207vX8Kd8BWNg/vprv/1/ns/Uf-YSjX6FTBnFx5chVngiDoS/playlist_type/CLEAN/dover/11/txp/5319224/mt/1771465040/fvip/4/keepalive/yes/fexp/51552689,51565115,51565681,51580968/n/5QXbrVPaUL9xXA/sparams/expire,ei,ip,id,itag,source,requiressl,ratebypass,pfa,sgoap,sgovp,rqh,xpc,siu,bui,spc,vprv,ns,playlist_type/sig/AJEij0EwRAIgBDte3cIs_vwlDanIkxpeqaZJfZLBW3Ns4v_UpT7QsUMCID7jWlRSFnP3hgXTJgGksZJ9WHBLEJIkwkNoptA4LNto/lsparams/hls_chunk_host,cps,met,mh,mm,mn,ms,mv,mvi,pl,rms,initcwndbps/lsig/APaTxxMwRQIhAL1b9K-zfd3YMThvYQSMwweKnasjUn5AWBqhbUZSOvs1AiAIywuFauYf_z3KObNJrw3HHB58gaSl5S59hdVePQIbeg%3D%3D/playlist/index.m3u8", "manifest_url": "https://manifest.googlevideo.com/api/manifest/hls_variant/expire/1771486998/ei/tmqWaabTHPeEp-oPhMnRkAg/ip/89.201.137.96/id/1f5d24949cbfe4bf/source/youtube/requiressl/yes/xpc/EgVo2aDSNQ%3D%3D/playback_host/rr2---sn-v2uph5-15bl.googlevideo.com/cps/301/met/1771465398%2C/mh/iZ/mm/31%2C29/mn/sn-v2uph5-15bl%2Csn-4g5lznlz/ms/au%2Crdu/mv/m/mvi/2/pl/18/rms/au%2Cau/tx/0/txs/51691027%2C51691028/hfr/1/maxh/4320/tts_caps/1/maudio/1/initcwndbps/1381250/siu/1/bui/AVNa5-y7i3PaLcsnsmCsFzb1k8LP2OcGpISlBzUou0f-z8n-QWRjhv-n_sXFNWRtV5zU15TUng/spc/6dlaFFE1c59rotXWGMW_Riy9bK3-Ac38KLMKJOjLWzbzQhAqJpnLXKjJaPqfw207vX8Kd8BWNg/vprv/1/go/1/ns/Uf-YSjX6FTBnFx5chVngiDoS/rqh/5/mt/1771465040/fvip/4/nvgoi/1/ncsapi/1/keepalive/yes/fexp/51552689%2C51565115%2C51565681%2C51580968/dover/11/n/5QXbrVPaUL9xXA/itag/0/playlist_type/CLEAN/sparams/expire%2Cei%2Cip%2Cid%2Csource%2Crequiressl%2Cxpc%2Ctx%2Ctxs%2Chfr%2Cmaxh%2Ctts_caps%2Cmaudio%2Csiu%2Cbui%2Cspc%2Cvprv%2Cgo%2Cns%2Crqh%2Citag%2Cplaylist_type/sig/AJEij0EwRQIhAM_IG0MpoB93ZlTshxjliV4kYhOLDkH94QA2k34Y99lEAiAPVQR4KyfXusxQg63wuKrDw2R78-ZFQip5qWr6Dh-xvw%3D%3D/lsparams/playback_host%2Ccps%2Cmet%2Cmh%2Cmm%2Cmn%2Cms%2Cmv%2Cmvi%2Cpl%2Crms%2Cinitcwndbps/lsig/APaTxxMwRgIhAI6UfH4FYgt3iMgPvDqx4wKtWc-Ds7e_LZQPLq9xTLBSAiEAwWRybtxu53IzGJDT0_uBJDQKKCP9IlaaBbvF98PICKM%3D/file/index.m3u8", "tbr": 459.118, "ext": "mp4", "fps": 30.0, "protocol": "m3u8_native", "quality": 6, "has_drm": false, "width": 640, "height": 360, "vcodec": "avc1.4D401E", "acodec": "mp4a.40.2", "dynamic_range": "SDR", "available_at": 1771465404, "source_preference": -2, "video_ext": "mp4", "audio_ext": "none", "resolution": "640x360", "aspect_ratio": 1.78, "http_headers": {"User-Agent": "Mozilla/5.0 (Macintosh; Intel Mac OS X 10_15_7) AppleWebKit/537.36 (KHTML, like Gecko) Chrome/144.0.0.0 Safari/537.36", "Accept": "text/html,application/xhtml+xml,application/xml;q=0.9,*/*;q=0.8", "Accept-Language": "en-us,en;q=0.5", "Sec-Fetch-Mode": "navigate"}, "format": "93 - 640x360"}, {"filesize": 27944192, "format_id": "134", "format_note": "360p", "source_preference": -1, "fps": 30, "height": 360, "quality": 6.0, "has_drm": false, "tbr": 221.587, "filesize_approx": 27944170, "width": 640, "language_preference": -1, "ext": "mp4", "vcodec": "avc1.4d401e", "acodec": "none", "dynamic_range": "SDR", "container": "mp4_dash", "url": "https://rr2---sn-v2uph5-15bl.googlevideo.com/videoplayback?expire=1771486998&ei=tmqWad6JB8zRp-oPn4qYoAE&ip=89.201.137.96&id=o-APkTk5Uee1RPQeTL8w9Pzpa1Rdl0B7eAWb25hqodAzuj&itag=134&aitags=134%2C136%2C160%2C243&source=youtube&requiressl=yes&xpc=EgVo2aDSNQ%3D%3D&cps=296&met=1771465398%2C&mh=iZ&mm=31%2C29&mn=sn-v2uph5-15bl%2Csn-4g5lznlz&ms=au%2Crdu&mv=m&mvi=2&pl=18&rms=au%2Cau&initcwndbps=1381250&siu=1&bui=AVNa5-yf63HS3uadg3T4kTGIF28DcrCQYbQ82e7wzj6PPEMtgkN4ABIQc9gcgx7y05IZdnTKxw&vprv=1&svpuc=1&mime=video%2Fmp4&ns=-oQLUN7Q2868RpGNEmNHDDoS&rqh=1&gir=yes&clen=27944192&dur=1008.874&lmt=1659291511089322&mt=1771465040&fvip=4&keepalive=yes&lmw=1&fexp=51557447%2C51565115%2C51565681%2C51580970%2C51759074&c=TVHTML5&sefc=1&txp=5319224&n=7hP55SJY84Aidg&sparams=expire%2Cei%2Cip%2Cid%2Caitags%2Csource%2Crequiressl%2Cxpc%2Csiu%2Cbui%2Cvprv%2Csvpuc%2Cmime%2Cns%2Crqh%2Cgir%2Cclen%2Cdur%2Clmt&sig=AJEij0EwRQIhAKBZiWanP_4vetUfDJcUU_8jnSxgpVkm1Fk9tTToUbm7AiBsQInPHW0UDS_v2FDYpVfHw_zY9HG37pYOv4BUHXKmuQ%3D%3D&lsparams=cps%2Cmet%2Cmh%2Cmm%2Cmn%2Cms%2Cmv%2Cmvi%2Cpl%2Crms%2Cinitcwndbps&lsig=APaTxxMwRQIgJJ1ExT2Sgn6XFqcV-JoWL57A7L7zcAFHEmBTJ8rhOskCIQCfZzXBiOqeN4lzfxq6PdpepP776AsG6AsZXAkL-k94tQ%3D%3D", "available_at": 1771465398, "downloader_options": {"http_chunk_size": 10485760}, "protocol": "https", "video_ext": "mp4", "audio_ext": "none", "abr": 0, "vbr": 221.587, "resolution": "640x360", "aspect_ratio": 1.78, "http_headers": {"User-Agent": "Mozilla/5.0 (Macintosh; Intel Mac OS X 10_15_7) AppleWebKit/537.36 (KHTML, like Gecko) Chrome/144.0.0.0 Safari/537.36", "Accept": "text/html,application/xhtml+xml,application/xml;q=0.9,*/*;q=0.8", "Accept-Language": "en-us,en;q=0.5", "Sec-Fetch-Mode": "navigate"}, "format": "134 - 640x360 (360p)"}, {"asr": 44100, "format_id": "18", "format_note": "360p", "source_preference": -1, "fps": 30, "audio_channels": 2, "height": 360, "quality": 6.0, "has_drm": false, "tbr": 349.74, "filesize_approx": 44108902, "width": 640, "language_preference": -1, "ext": "mp4", "vcodec": "avc1.42001E", "acodec": "mp4a.40.2", "dynamic_range": "SDR", "url": "https://rr2---sn-v2uph5-15bl.googlevideo.com/videoplayback?expire=1771486998&ei=tmqWad6JB8zRp-oPn4qYoAE&ip=89.201.137.96&id=o-APkTk5Uee1RPQeTL8w9Pzpa1Rdl0B7eAWb25hqodAzuj&itag=18&source=youtube&requiressl=yes&xpc=EgVo2aDSNQ%3D%3D&cps=296&met=1771465398%2C&mh=iZ&mm=31%2C29&mn=sn-v2uph5-15bl%2Csn-4g5lznlz&ms=au%2Crdu&mv=m&mvi=2&pl=18&rms=au%2Cau&initcwndbps=1381250&siu=1&bui=AVNa5-ybYALZVcIUqs_d8LaOeRHQSrAqa9Q-16_zXcN5YPS_Z1Im21rCga3LkFn3MZL5QNrK_g&vprv=1&svpuc=1&mime=video%2Fmp4&ns=ivCaASHxaPLWaCP-d7gS-OsS&rqh=1&cnr=14&ratebypass=yes&dur=1008.953&lmt=1665073551868172&mt=1771465040&fvip=4&lmw=1&fexp=51557447%2C51565115%2C51565681%2C51580970%2C51759074&c=TVHTML5&sefc=1&txp=5318224&n=Aj0jd5vRTjDZlw&sparams=expire%2Cei%2Cip%2Cid%2Citag%2Csource%2Crequiressl%2Cxpc%2Csiu%2Cbui%2Cvprv%2Csvpuc%2Cmime%2Cns%2Crqh%2Ccnr%2Cratebypass%2Cdur%2Clmt&sig=AJEij0EwRQIgJxugYgO1QtM58iSno-0EvShLbcE50va0_4QtvOjuy2wCIQDDLLgRiv9qeWaduRkNHKv0ZjXY2SrVshug7lhf9oK2kw%3D%3D&lsparams=cps%2Cmet%2Cmh%2Cmm%2Cmn%2Cms%2Cmv%2Cmvi%2Cpl%2Crms%2Cinitcwndbps&lsig=APaTxxMwRQIgJJ1ExT2Sgn6XFqcV-JoWL57A7L7zcAFHEmBTJ8rhOskCIQCfZzXBiOqeN4lzfxq6PdpepP776AsG6AsZXAkL-k94tQ%3D%3D", "available_at": 1771465398, "downloader_options": {"http_chunk_size": 10485760}, "protocol": "https", "video_ext": "mp4", "audio_ext": "none", "resolution": "640x360", "aspect_ratio": 1.78, "http_headers": {"User-Agent": "Mozilla/5.0 (Macintosh; Intel Mac OS X 10_15_7) AppleWebKit/537.36 (KHTML, like Gecko) Chrome/144.0.0.0 Safari/537.36", "Accept": "text/html,application/xhtml+xml,application/xml;q=0.9,*/*;q=0.8", "Accept-Language": "en-us,en;q=0.5", "Sec-Fetch-Mode": "navigate"}, "format": "18 - 640x360 (360p)"}, {"filesize": 16380499, "format_id": "243", "format_note": "360p", "source_preference": -1, "fps": 30, "height": 360, "quality": 6.0, "has_drm": false, "tbr": 129.891, "filesize_approx": 16380456, "width": 640, "language_preference": -1, "ext": "webm", "vcodec": "vp9", "acodec": "none", "dynamic_range": "SDR", "container": "webm_dash", "url": "https://rr2---sn-v2uph5-15bl.googlevideo.com/videoplayback?expire=1771486998&ei=tmqWad6JB8zRp-oPn4qYoAE&ip=89.201.137.96&id=o-APkTk5Uee1RPQeTL8w9Pzpa1Rdl0B7eAWb25hqodAzuj&itag=243&aitags=134%2C136%2C160%2C243&source=youtube&requiressl=yes&xpc=EgVo2aDSNQ%3D%3D&cps=296&met=1771465398%2C&mh=iZ&mm=31%2C29&mn=sn-v2uph5-15bl%2Csn-4g5lznlz&ms=au%2Crdu&mv=m&mvi=2&pl=18&rms=au%2Cau&initcwndbps=1381250&siu=1&bui=AVNa5-yf63HS3uadg3T4kTGIF28DcrCQYbQ82e7wzj6PPEMtgkN4ABIQc9gcgx7y05IZdnTKxw&vprv=1&svpuc=1&mime=video%2Fwebm&ns=-oQLUN7Q2868RpGNEmNHDDoS&rqh=1&gir=yes&clen=16380499&dur=1008.874&lmt=1659291606150838&mt=1771465040&fvip=4&keepalive=yes&lmw=1&fexp=51557447%2C51565115%2C51565681%2C51580970%2C51759074&c=TVHTML5&sefc=1&txp=5319224&n=7hP55SJY84Aidg&sparams=expire%2Cei%2Cip%2Cid%2Caitags%2Csource%2Crequiressl%2Cxpc%2Csiu%2Cbui%2Cvprv%2Csvpuc%2Cmime%2Cns%2Crqh%2Cgir%2Cclen%2Cdur%2Clmt&sig=AJEij0EwRQIgUGebOkCS9an8SPbqzrfkhvIbTY-WdhmkARVihCvWgVkCIQDKcKwDeZKFRnIo6CzsJTGCDbp7GJmCnDBlTNfvNhL5Kw%3D%3D&lsparams=cps%2Cmet%2Cmh%2Cmm%2Cmn%2Cms%2Cmv%2Cmvi%2Cpl%2Crms%2Cinitcwndbps&lsig=APaTxxMwRQIgJJ1ExT2Sgn6XFqcV-JoWL57A7L7zcAFHEmBTJ8rhOskCIQCfZzXBiOqeN4lzfxq6PdpepP776AsG6AsZXAkL-k94tQ%3D%3D", "available_at": 1771465398, "downloader_options": {"http_chunk_size": 10485760}, "protocol": "https", "video_ext": "webm", "audio_ext": "none", "abr": 0, "vbr": 129.891, "resolution": "640x360", "aspect_ratio": 1.78, "http_headers": {"User-Agent": "Mozilla/5.0 (Macintosh; Intel Mac OS X 10_15_7) AppleWebKit/537.36 (KHTML, like Gecko) Chrome/144.0.0.0 Safari/537.36", "Accept": "text/html,application/xhtml+xml,application/xml;q=0.9,*/*;q=0.8", "Accept-Language": "en-us,en;q=0.5", "Sec-Fetch-Mode": "navigate"}, "format": "243 - 640x360 (360p)"}, {"format_id": "95", "url": "https://manifest.googlevideo.com/api/manifest/hls_playlist/expire/1771486998/ei/tmqWaabTHPeEp-oPhMnRkAg/ip/89.201.137.96/id/1f5d24949cbfe4bf/itag/95/source/youtube/requiressl/yes/ratebypass/yes/pfa/1/sgoap/clen%3D16329559%3Bdur%3D1008.953%3Bgir%3Dyes%3Bitag%3D140%3Blmt%3D1659290272142056/sgovp/clen%3D96459249%3Bdur%3D1008.874%3Bgir%3Dyes%3Bitag%3D136%3Blmt%3D1659290218346652/rqh/1/hls_chunk_host/rr2---sn-v2uph5-15bl.googlevideo.com/xpc/EgVo2aDSNQ%3D%3D/cps/301/met/1771465398,/mh/iZ/mm/31,29/mn/sn-v2uph5-15bl,sn-4g5lznlz/ms/au,rdu/mv/m/mvi/2/pl/18/rms/au,au/initcwndbps/1381250/siu/1/bui/AVNa5-y7i3PaLcsnsmCsFzb1k8LP2OcGpISlBzUou0f-z8n-QWRjhv-n_sXFNWRtV5zU15TUng/spc/6dlaFFE1c59rotXWGMW_Riy9bK3-Ac38KLMKJOjLWzbzQhAqJpnLXKjJaPqfw207vX8Kd8BWNg/vprv/1/ns/Uf-YSjX6FTBnFx5chVngiDoS/playlist_type/CLEAN/dover/11/txp/5319224/mt/1771465040/fvip/4/keepalive/yes/fexp/51552689,51565115,51565681,51580968/n/5QXbrVPaUL9xXA/sparams/expire,ei,ip,id,itag,source,requiressl,ratebypass,pfa,sgoap,sgovp,rqh,xpc,siu,bui,spc,vprv,ns,playlist_type/sig/AJEij0EwRAIgGjksD5AtBdFx1sqsxAxrlDe_1_7mVsEQ4pGG7uh5Ej4CIC1rtppDJtAXHOCaLbTO33QqyH5oNDLMlvWTyRgyggTl/lsparams/hls_chunk_host,cps,met,mh,mm,mn,ms,mv,mvi,pl,rms,initcwndbps/lsig/APaTxxMwRgIhALIvt7mkTUYqs_UoVxvWJAUIkiEmgP4mRDLqjG-_UnIiAiEA1wmGRVmuFpMKvs_18jWpVepJss4HCww4G_5jfbKM7wg%3D/playlist/index.m3u8", "manifest_url": "https://manifest.googlevideo.com/api/manifest/hls_variant/expire/1771486998/ei/tmqWaabTHPeEp-oPhMnRkAg/ip/89.201.137.96/id/1f5d24949cbfe4bf/source/youtube/requiressl/yes/xpc/EgVo2aDSNQ%3D%3D/playback_host/rr2---sn-v2uph5-15bl.googlevideo.com/cps/301/met/1771465398%2C/mh/iZ/mm/31%2C29/mn/sn-v2uph5-15bl%2Csn-4g5lznlz/ms/au%2Crdu/mv/m/mvi/2/pl/18/rms/au%2Cau/tx/0/txs/51691027%2C51691028/hfr/1/maxh/4320/tts_caps/1/maudio/1/initcwndbps/1381250/siu/1/bui/AVNa5-y7i3PaLcsnsmCsFzb1k8LP2OcGpISlBzUou0f-z8n-QWRjhv-n_sXFNWRtV5zU15TUng/spc/6dlaFFE1c59rotXWGMW_Riy9bK3-Ac38KLMKJOjLWzbzQhAqJpnLXKjJaPqfw207vX8Kd8BWNg/vprv/1/go/1/ns/Uf-YSjX6FTBnFx5chVngiDoS/rqh/5/mt/1771465040/fvip/4/nvgoi/1/ncsapi/1/keepalive/yes/fexp/51552689%2C51565115%2C51565681%2C51580968/dover/11/n/5QXbrVPaUL9xXA/itag/0/playlist_type/CLEAN/sparams/expire%2Cei%2Cip%2Cid%2Csource%2Crequiressl%2Cxpc%2Ctx%2Ctxs%2Chfr%2Cmaxh%2Ctts_caps%2Cmaudio%2Csiu%2Cbui%2Cspc%2Cvprv%2Cgo%2Cns%2Crqh%2Citag%2Cplaylist_type/sig/AJEij0EwRQIhAM_IG0MpoB93ZlTshxjliV4kYhOLDkH94QA2k34Y99lEAiAPVQR4KyfXusxQg63wuKrDw2R78-ZFQip5qWr6Dh-xvw%3D%3D/lsparams/playback_host%2Ccps%2Cmet%2Cmh%2Cmm%2Cmn%2Cms%2Cmv%2Cmvi%2Cpl%2Crms%2Cinitcwndbps/lsig/APaTxxMwRgIhAI6UfH4FYgt3iMgPvDqx4wKtWc-Ds7e_LZQPLq9xTLBSAiEAwWRybtxu53IzGJDT0_uBJDQKKCP9IlaaBbvF98PICKM%3D/file/index.m3u8", "tbr": 1334.418, "ext": "mp4", "fps": 30.0, "protocol": "m3u8_native", "quality": 8, "has_drm": false, "width": 1280, "height": 720, "vcodec": "avc1.64001F", "acodec": "mp4a.40.2", "dynamic_range": "SDR", "available_at": 1771465404, "source_preference": -2, "video_ext": "mp4", "audio_ext": "none", "resolution": "1280x720", "aspect_ratio": 1.78, "http_headers": {"User-Agent": "Mozilla/5.0 (Macintosh; Intel Mac OS X 10_15_7) AppleWebKit/537.36 (KHTML, like Gecko) Chrome/144.0.0.0 Safari/537.36", "Accept": "text/html,application/xhtml+xml,application/xml;q=0.9,*/*;q=0.8", "Accept-Language": "en-us,en;q=0.5", "Sec-Fetch-Mode": "navigate"}, "format": "95 - 1280x720"}, {"filesize": 96459249, "format_id": "136", "format_note": "720p", "source_preference": -1, "fps": 30, "height": 720, "quality": 8.0, "has_drm": false, "tbr": 764.886, "filesize_approx": 96459199, "width": 1280, "language_preference": -1, "ext": "mp4", "vcodec": "avc1.64001f", "acodec": "none", "dynamic_range": "SDR", "container": "mp4_dash", "url": "https://rr2---sn-v2uph5-15bl.googlevideo.com/videoplayback?expire=1771486998&ei=tmqWad6JB8zRp-oPn4qYoAE&ip=89.201.137.96&id=o-APkTk5Uee1RPQeTL8w9Pzpa1Rdl0B7eAWb25hqodAzuj&itag=136&aitags=134%2C136%2C160%2C243&source=youtube&requiressl=yes&xpc=EgVo2aDSNQ%3D%3D&cps=296&met=1771465398%2C&mh=iZ&mm=31%2C29&mn=sn-v2uph5-15bl%2Csn-4g5lznlz&ms=au%2Crdu&mv=m&mvi=2&pl=18&rms=au%2Cau&initcwndbps=1381250&siu=1&bui=AVNa5-yf63HS3uadg3T4kTGIF28DcrCQYbQ82e7wzj6PPEMtgkN4ABIQc9gcgx7y05IZdnTKxw&vprv=1&svpuc=1&mime=video%2Fmp4&ns=-oQLUN7Q2868RpGNEmNHDDoS&rqh=1&gir=yes&clen=96459249&dur=1008.874&lmt=1659290218346652&mt=1771465040&fvip=4&keepalive=yes&lmw=1&fexp=51557447%2C51565115%2C51565681%2C51580970%2C51759074&c=TVHTML5&sefc=1&txp=5319224&n=7hP55SJY84Aidg&sparams=expire%2Cei%2Cip%2Cid%2Caitags%2Csource%2Crequiressl%2Cxpc%2Csiu%2Cbui%2Cvprv%2Csvpuc%2Cmime%2Cns%2Crqh%2Cgir%2Cclen%2Cdur%2Clmt&sig=AJEij0EwRAIgbnHcfb1kI1MUQ9LkplAsZuli4bE0mZJezQEa1LCiUXMCICW_AVHSIOQaeN5sgpTML6C3CEMWIX0VlR9DkZ4UeBga&lsparams=cps%2Cmet%2Cmh%2Cmm%2Cmn%2Cms%2Cmv%2Cmvi%2Cpl%2Crms%2Cinitcwndbps&lsig=APaTxxMwRQIgJJ1ExT2Sgn6XFqcV-JoWL57A7L7zcAFHEmBTJ8rhOskCIQCfZzXBiOqeN4lzfxq6PdpepP776AsG6AsZXAkL-k94tQ%3D%3D", "available_at": 1771465398, "downloader_options": {"http_chunk_size": 10485760}, "protocol": "https", "video_ext": "mp4", "audio_ext": "none", "abr": 0, "vbr": 764.886, "resolution": "1280x720", "aspect_ratio": 1.78, "http_headers": {"User-Agent": "Mozilla/5.0 (Macintosh; Intel Mac OS X 10_15_7) AppleWebKit/537.36 (KHTML, like Gecko) Chrome/144.0.0.0 Safari/537.36", "Accept": "text/html,application/xhtml+xml,application/xml;q=0.9,*/*;q=0.8", "Accept-Language": "en-us,en;q=0.5", "Sec-Fetch-Mode": "navigate"}, "format": "136 - 1280x720 (720p)"}], "thumbnails": [{"url": "https://i.ytimg.com/vi/H10klJy_5L8/3.jpg", "preference": -37, "id": "0"}, {"url": "https://i.ytimg.com/vi_webp/H10klJy_5L8/3.webp", "preference": -36, "id": "1"}, {"url": "https://i.ytimg.com/vi/H10klJy_5L8/2.jpg", "preference": -35, "id": "2"}, {"url": "https://i.ytimg.com/vi_webp/H10klJy_5L8/2.webp", "preference": -34, "id": "3"}, {"url": "https://i.ytimg.com/vi/H10klJy_5L8/1.jpg", "preference": -33, "id": "4"}, {"url": "https://i.ytimg.com/vi_webp/H10klJy_5L8/1.webp", "preference": -32, "id": "5"}, {"url": "https://i.ytimg.com/vi/H10klJy_5L8/mq3.jpg", "preference": -31, "id": "6"}, {"url": "https://i.ytimg.com/vi_webp/H10klJy_5L8/mq3.webp", "preference": -30, "id": "7"}, {"url": "https://i.ytimg.com/vi/H10klJy_5L8/mq2.jpg", "preference": -29, "id": "8"}, {"url": "https://i.ytimg.com/vi_webp/H10klJy_5L8/mq2.webp", "preference": -28, "id": "9"}, {"url": "https://i.ytimg.com/vi/H10klJy_5L8/mq1.jpg", "preference": -27, "id": "10"}, {"url": "https://i.ytimg.com/vi_webp/H10klJy_5L8/mq1.webp", "preference": -26, "id": "11"}, {"url": "https://i.ytimg.com/vi/H10klJy_5L8/hq3.jpg", "preference": -25, "id": "12"}, {"url": "https://i.ytimg.com/vi_webp/H10klJy_5L8/hq3.webp", "preference": -24, "id": "13"}, {"url": "https://i.ytimg.com/vi/H10klJy_5L8/hq2.jpg", "preference": -23, "id": "14"}, {"url": "https://i.ytimg.com/vi_webp/H10klJy_5L8/hq2.webp", "preference": -22, "id": "15"}, {"url": "https://i.ytimg.com/vi/H10klJy_5L8/hq1.jpg", "preference": -21, "id": "16"}, {"url": "https://i.ytimg.com/vi_webp/H10klJy_5L8/hq1.webp", "preference": -20, "id": "17"}, {"url": "https://i.ytimg.com/vi/H10klJy_5L8/sd3.jpg", "preference": -19, "id": "18"}, {"url": "https://i.ytimg.com/vi_webp/H10klJy_5L8/sd3.webp", "preference": -18, "id": "19"}, {"url": "https://i.ytimg.com/vi/H10klJy_5L8/sd2.jpg", "preference": -17, "id": "20"}, {"url": "https://i.ytimg.com/vi_webp/H10klJy_5L8/sd2.webp", "preference": -16, "id": "21"}, {"url": "https://i.ytimg.com/vi/H10klJy_5L8/sd1.jpg", "preference": -15, "id": "22"}, {"url": "https://i.ytimg.com/vi_webp/H10klJy_5L8/sd1.webp", "preference": -14, "id": "23"}, {"url": "https://i.ytimg.com/vi/H10klJy_5L8/default.jpg", "preference": -13, "id": "24"}, {"url": "https://i.ytimg.com/vi_webp/H10klJy_5L8/default.webp", "preference": -12, "id": "25"}, {"url": "https://i.ytimg.com/vi/H10klJy_5L8/mqdefault.jpg", "preference": -11, "id": "26"}, {"url": "https://i.ytimg.com/vi_webp/H10klJy_5L8/mqdefault.webp", "preference": -10, "id": "27"}, {"url": "https://i.ytimg.com/vi/H10klJy_5L8/0.jpg", "preference": -9, "id": "28"}, {"url": "https://i.ytimg.com/vi_webp/H10klJy_5L8/0.webp", "preference": -8, "id": "29"}, {"url": "https://i.ytimg.com/vi/H10klJy_5L8/hqdefault.jpg?sqp=-oaymwEbCKgBEF5IVfKriqkDDggBFQAAiEIYAXABwAEG&rs=AOn4CLDu5gr498Lwh_zINZlAaVnkaWGxXQ", "height": 94, "width": 168, "preference": -7, "id": "30", "resolution": "168x94"}, {"url": "https://i.ytimg.com/vi/H10klJy_5L8/hqdefault.jpg?sqp=-oaymwEiCKgBEF5IWvKriqkDFQgBFQAAAAAYASUAAMhCPQCAokN4AQ==&rs=AOn4CLCGRaYAUF-Y2g3xm1CE7glEQtD24A", "height": 94, "width": 168, "preference": -7, "id": "31", "resolution": "168x94"}, {"url": "https://i.ytimg.com/vi/H10klJy_5L8/hqdefault.jpg?sqp=-oaymwEbCMQBEG5IVfKriqkDDggBFQAAiEIYAXABwAEG&rs=AOn4CLC6SttrGesvYDTPPok5pBOQee33sw", "height": 110, "width": 196, "preference": -7, "id": "32", "resolution": "196x110"}, {"url": "https://i.ytimg.com/vi/H10klJy_5L8/hqdefault.jpg?sqp=-oaymwEiCMQBEG5IWvKriqkDFQgBFQAAAAAYASUAAMhCPQCAokN4AQ==&rs=AOn4CLCRG-5j2wa0Iq7JimbYBP51Nk7hfg", "height": 110, "width": 196, "preference": -7, "id": "33", "resolution": "196x110"}, {"url": "https://i.ytimg.com/vi/H10klJy_5L8/hqdefault.jpg?sqp=-oaymwEcCPYBEIoBSFXyq4qpAw4IARUAAIhCGAFwAcABBg==&rs=AOn4CLAyYjHm1fSOOg1eNsoxcY-N4h3KMg", "height": 138, "width": 246, "preference": -7, "id": "34", "resolution": "246x138"}, {"url": "https://i.ytimg.com/vi/H10klJy_5L8/hqdefault.jpg?sqp=-oaymwEjCPYBEIoBSFryq4qpAxUIARUAAAAAGAElAADIQj0AgKJDeAE=&rs=AOn4CLDjDC1Jip4k7OZXbBvxwN-yfp9KYA", "height": 138, "width": 246, "preference": -7, "id": "35", "resolution": "246x138"}, {"url": "https://i.ytimg.com/vi/H10klJy_5L8/hqdefault.jpg?sqp=-oaymwEcCNACELwBSFXyq4qpAw4IARUAAIhCGAFwAcABBg==&rs=AOn4CLBIwR05QzAnaZ4WeKrW1IgIIOKfKw", "height": 188, "width": 336, "preference": -7, "id": "36", "resolution": "336x188"}, {"url": "https://i.ytimg.com/vi/H10klJy_5L8/hqdefault.jpg?sqp=-oaymwEjCNACELwBSFryq4qpAxUIARUAAAAAGAElAADIQj0AgKJDeAE=&rs=AOn4CLBM9w7PBv46BiITLu4qRARg-e4QGA", "height": 188, "width": 336, "preference": -7, "id": "37", "resolution": "336x188"}, {"url": "https://i.ytimg.com/vi/H10klJy_5L8/hqdefault.jpg", "height": 360, "width": 480, "preference": -7, "id": "38", "resolution": "480x360"}, {"url": "https://i.ytimg.com/vi_webp/H10klJy_5L8/hqdefault.webp", "preference": -6, "id": "39"}, {"url": "https://i.ytimg.com/vi/H10klJy_5L8/sddefault.jpg", "preference": -5, "id": "40"}, {"url": "https://i.ytimg.com/vi_webp/H10klJy_5L8/sddefault.webp", "preference": -4, "id": "41"}, {"url": "https://i.ytimg.com/vi/H10klJy_5L8/hq720.jpg", "preference": -3, "id": "42"}, {"url": "https://i.ytimg.com/vi_webp/H10klJy_5L8/hq720.webp", "preference": -2, "id": "43"}, {"url": "https://i.ytimg.com/vi/H10klJy_5L8/maxresdefault.jpg", "height": 1080, "width": 1920, "preference": -1, "id": "44", "resolution": "1920x1080"}, {"url": "https://i.ytimg.com/vi_webp/H10klJy_5L8/maxresdefault.webp", "preference": 0, "id": "45"}], "thumbnail": "https://i.ytimg.com/vi/H10klJy_5L8/maxresdefault.jpg", "description": "Zapamti: ako imaš vremena kukati - imaš vremena promijeniti ono zbog čega kukaš. Ne gubi vrijeme na beskorisno gunđanje koje ne vodi cilju, radije umjesto te navike (da, kukanje je \"samo\" navika, a nije urođena mana ;)) pokušaj razviti neku pozitivnu i zdravu naviku. Malim koracima gradi veliku pozitivnu promjenu u svom životu, ali i u životima ljudi oko sebe! Sretno! :**\n\nZaprati me na tiktoku i Instagramu ako želiš (@mrs.kraljevic)\nOvo je moj webshop s planerima, hoodicama i drugim stvarima: https://www.iktusplan.com\nPiši mi na mail: ivakraljevic1712@gmail.com", "channel_id": "UCT6Sx8T7walJ0dpOgqHllkw", "channel_url": "https://www.youtube.com/channel/UCT6Sx8T7walJ0dpOgqHllkw", "duration": 1009, "view_count": 3926, "age_limit": 0, "webpage_url": "https://www.youtube.com/watch?v=H10klJy_5L8", "categories": ["People & Blogs"], "tags": [], "playable_in_embed": true, "live_status": "not_live", "media_type": "video", "_format_sort_fields": ["quality", "res", "fps", "hdr:12", "source", "vcodec", "channels", "acodec", "lang", "proto"], "automatic_captions": {}, "subtitles": {}, "comment_count": 6, "like_count": 152, "channel": "Iva Kraljevic", "channel_follower_count": 27200, "uploader": "Iva Kraljevic", "uploader_id": "@ivakraljevic.", "uploader_url": "https://www.youtube.com/@ivakraljevic.", "upload_date": "20220729", "timestamp": 1659103214, "availability": "public", "webpage_url_basename": "watch", "webpage_url_domain": "youtube.com", "extractor": "youtube", "extractor_key": "Youtube", "display_id": "H10klJy_5L8", "fulltitle": "ZABRANJENO KUKANJE - knjiga po Papinoj preporuci! // Kako se osloboditi kukanja?", "duration_string": "16:49", "is_live": false, "was_live": false, "epoch": 1771465399, "format": "243 - 640x360 (360p)+251 - audio only (medium)", "format_id": "243+251", "ext": "webm", "protocol": "https+https", "format_note": "360p+medium", "filesize_approx": 29219001, "tbr": 231.69, "width": 640, "height": 360, "resolution": "640x360", "fps": 30, "dynamic_range": "SDR", "vcodec": "vp9", "vbr": 129.891, "aspect_ratio": 1.78, "acodec": "opus", "abr": 101.799, "asr": 48000, "audio_channels": 2, "_type": "video", "_version": {"version": "2026.02.04", "release_git_head": "c677d866d41eb4075b0a5e0c944a6543fc13f15d", "repository": "yt-dlp/yt-dlp"}}