{
  "base": "20230205_marko_babic_putovanje_zvano_igra_yt_ZaAfKh2DuXw",
  "channel": "lood_podcast",
  "target": {
    "I": -16,
    "TP": -2,
    "LRA": 11
  },
  "method": "loudnorm single-pass dynamic (Dynamic)",
  "audio_source": {
    "file": "20230205_marko_babic_putovanje_zvano_igra_yt_ZaAfKh2DuXw.mkv",
    "type": "mkv"
  },
  "input": {
    "integrated_lufs": -15.8,
    "true_peak_dbtp": null,
    "lra": 4.7
  },
  "output": {
    "integrated_lufs": -15.7,
    "true_peak_dbtp": -2
  },
  "formats": {
    "mp3": {
      "output": "20230205_marko_babic_putovanje_zvano_igra_yt_ZaAfKh2DuXw.loudnorm.mp3",
      "bitrate": "128k",
      "normalized_at": "2026-05-29T00:55:46.419Z"
    }
  }
}
