{
  "base": "20230303_josip_bilandzija_umalo_ugasena_milost_yt_4I1nX0JaFak",
  "channel": "kko_hr",
  "target": {
    "I": -16,
    "TP": -2,
    "LRA": 11
  },
  "method": "loudnorm single-pass dynamic (Dynamic)",
  "audio_source": {
    "file": "20230303_josip_bilandzija_umalo_ugasena_milost_yt_4I1nX0JaFak.mkv",
    "type": "mkv"
  },
  "input": {
    "integrated_lufs": -15.9,
    "true_peak_dbtp": -0.5,
    "lra": 5.2
  },
  "output": {
    "integrated_lufs": -15.9,
    "true_peak_dbtp": -2
  },
  "formats": {
    "mp3": {
      "output": "20230303_josip_bilandzija_umalo_ugasena_milost_yt_4I1nX0JaFak.loudnorm.mp3",
      "bitrate": "128k",
      "normalized_at": "2026-05-29T00:21:25.764Z"
    }
  }
}
