{
  "base": "20210420_55_minuta_kod_zeljke_markic_36_jakov_sedlar_yt_0ksMujc7jD4",
  "channel": "zeljka_markic_i_narod_hr",
  "target": {
    "I": -16,
    "TP": -2,
    "LRA": 11
  },
  "method": "loudnorm single-pass dynamic (Dynamic)",
  "audio_source": {
    "file": "20210420_55_minuta_kod_zeljke_markic_36_jakov_sedlar_yt_0ksMujc7jD4.mkv",
    "type": "mkv"
  },
  "input": {
    "integrated_lufs": -10.5,
    "true_peak_dbtp": null,
    "lra": 3.9
  },
  "output": {
    "integrated_lufs": -16,
    "true_peak_dbtp": -4.1
  },
  "formats": {
    "mp3": {
      "output": "20210420_55_minuta_kod_zeljke_markic_36_jakov_sedlar_yt_0ksMujc7jD4.loudnorm.mp3",
      "bitrate": "128k",
      "normalized_at": "2026-05-29T09:00:10.394Z"
    }
  }
}
