{
  "id": "w9HAwvWKJQc",
  "title": "App Store Ethics, Dark Patterns, and Rule-Breakers — Steve P. Young, App Masters",
  "description": "On the podcast: “Black hat” app optimization, the benefits and drawbacks of hard paywalls, and why, despite Apple and Google’s best efforts, so many apps still use dark patterns and even blatantly break the rules.",
  "upload_date": "20230823",
  "timestamp": 1692781200,
  "duration": 2882,
  "view_count": 0,
  "like_count": 0,
  "uploader": "Sub Club by RevenueCat",
  "channel": "Sub Club by RevenueCat",
  "channel_id": "beamly_subclub",
  "channel_url": "https://subclub.com",
  "webpage_url": "https://subclub.com/episode/app-store-ethics-dark-patterns-and-rule-breakers-steve-p-young-app-masters",
  "thumbnail": "https://img.transistor.fm/MKrFDUeQ5WMEzDVZxbXwpLkJjgmzqAWgv0xEiyhVVwA/rs:fill:3000:3000:1/q:60/aHR0cHM6Ly9pbWct/dXBsb2FkLXByb2R1/Y3Rpb24udHJhbnNp/c3Rvci5mbS9lcGlz/b2RlLzE0NzAwMjIv/MTY5MjczNzI0My1h/cnR3b3JrLmpwZw.jpg",
  "_source": "beamly",
  "_beamly_id": "64e5ce1fde00a6825bdd8995",
  "_slug": "app-store-ethics-dark-patterns-and-rule-breakers-steve-p-young-app-masters",
  "_episode_number": "71",
  "_sound_link": "https://media.transistor.fm/c95515bd/cebdceff.mp3",
  "_yt_matched": true
}
