{
  "base": "20230503_2_srijeda_devetnice_u_cast_precistog_josipovog_srca_yt_S5Jk9M5ctkY",
  "channel": "merz_institut",
  "target": {
    "I": -16,
    "TP": -2,
    "LRA": 11
  },
  "method": "loudnorm single-pass dynamic (Dynamic)",
  "audio_source": {
    "file": "20230503_2_srijeda_devetnice_u_cast_precistog_josipovog_srca_yt_S5Jk9M5ctkY.mp4",
    "type": "mp4"
  },
  "input": {
    "integrated_lufs": -14.3,
    "true_peak_dbtp": null,
    "lra": 11
  },
  "output": {
    "integrated_lufs": -14.6,
    "true_peak_dbtp": -2
  },
  "formats": {
    "mp3": {
      "output": "20230503_2_srijeda_devetnice_u_cast_precistog_josipovog_srca_yt_S5Jk9M5ctkY.loudnorm.mp3",
      "bitrate": "128k",
      "normalized_at": "2026-05-29T02:24:06.804Z"
    }
  }
}
